swingmusic/__main__.py
swingmusic/app_builder.py
swingmusic/config.py
swingmusic/logger.py
swingmusic/periodic_scan.py
swingmusic/settings.py
swingmusic/start_info_logger.py
swingmusic/start_swingmusic.py
swingmusic/tools.py
swingmusic/api/__init__.py
swingmusic/api/album.py
swingmusic/api/apischemas.py
swingmusic/api/artist.py
swingmusic/api/auth.py
swingmusic/api/backup_and_restore.py
swingmusic/api/collections.py
swingmusic/api/colors.py
swingmusic/api/favorites.py
swingmusic/api/folder.py
swingmusic/api/imgserver.py
swingmusic/api/lyrics.py
swingmusic/api/playlist.py
swingmusic/api/search.py
swingmusic/api/settings.py
swingmusic/api/stream.py
swingmusic/api/getall/__init__.py
swingmusic/api/home/__init__.py
swingmusic/api/plugins/__init__.py
swingmusic/api/plugins/lyrics.py
swingmusic/api/plugins/mixes.py
swingmusic/api/scrobble/__init__.py
swingmusic/assets/album.svg
swingmusic/assets/artist.webp
swingmusic/assets/default.webp
swingmusic/assets/logo-fill.light.ico
swingmusic/assets/playlist.svg
swingmusic/crons/__init__.py
swingmusic/crons/cron.py
swingmusic/crons/mixes.py
swingmusic/data/artist_split_ignore.txt
swingmusic/db/__init__.py
swingmusic/db/engine.py
swingmusic/db/libdata.py
swingmusic/db/metadata.py
swingmusic/db/userdata.py
swingmusic/db/utils.py
swingmusic/db/sqlite/__init__.py
swingmusic/db/sqlite/migrations.py
swingmusic/db/sqlite/utils.py
swingmusic/enums/album_versions.py
swingmusic/jsoni/index.py
swingmusic/lib/__init__.py
swingmusic/lib/albumslib.py
swingmusic/lib/artistlib.py
swingmusic/lib/colorlib.py
swingmusic/lib/errors.py
swingmusic/lib/extras.py
swingmusic/lib/folderslib.py
swingmusic/lib/index.py
swingmusic/lib/lyrics.py
swingmusic/lib/mapstuff.py
swingmusic/lib/pagelib.py
swingmusic/lib/playlistlib.py
swingmusic/lib/populate.py
swingmusic/lib/searchlib.py
swingmusic/lib/sortlib.py
swingmusic/lib/tagger.py
swingmusic/lib/taglib.py
swingmusic/lib/trackslib.py
swingmusic/lib/transcoder.py
swingmusic/lib/watchdogg.py
swingmusic-2.1.10.dist-info/licenses/LICENSE
swingmusic-2.1.10.dist-info/METADATA
swingmusic-2.1.10.dist-info/WHEEL
swingmusic-2.1.10.dist-info/entry_points.txt
swingmusic-2.1.10.dist-info/top_level.txt
swingmusic-2.1.10.dist-info/RECORD
