Metadata-Version: 2.4
Name: swingmusic
Version: 2.1.10
Summary: Swing Music
Project-URL: Homepage, https://swingmx.com/
Project-URL: Repository, https://github.com/swingmx/swingmusic
Project-URL: Documentation, https://swingmx.com/guide/introduction.html
Project-URL: Issues, https://github.com/swingmx/swingmusic/issues
Requires-Python: >=3.11
License-File: LICENSE
Requires-Dist: pillow>=11.1.0
Requires-Dist: Flask>=3.1.0
Requires-Dist: Flask-Cors>=3.0.10
Requires-Dist: requests>=2.27.1
Requires-Dist: colorgram.py>=1.2.0
Requires-Dist: tqdm>=4.65.0
Requires-Dist: tinytag>=2.1.1
Requires-Dist: Unidecode>=1.3.6
Requires-Dist: psutil>=5.9.4
Requires-Dist: show-in-file-manager>=1.1.4
Requires-Dist: flask-compress>=1.13
Requires-Dist: tabulate>=0.9.0
Requires-Dist: setproctitle>=1.3.2
Requires-Dist: locust>=2.20.1
Requires-Dist: watchdog>=4.0.0
Requires-Dist: flask-jwt-extended>=4.6.0
Requires-Dist: sqlalchemy>=2.0.31
Requires-Dist: memory-profiler>=0.61.0
Requires-Dist: sortedcontainers>=2.4.0
Requires-Dist: xxhash>=3.4.1
Requires-Dist: ffmpeg-python>=0.2.0
Requires-Dist: schedule>=1.2.2
Requires-Dist: pillow>=11.1.0
Requires-Dist: flask-openapi3==3.0.2
Requires-Dist: rapidfuzz==3.11.0
Requires-Dist: pendulum>=3.0.0
Requires-Dist: pystray>=0.19.5
Requires-Dist: waitress>=3.0.2; sys_platform == "win32"
Requires-Dist: bjoern>=3.2.2; sys_platform != "win32"
Provides-Extra: build
Requires-Dist: pyinstaller; extra == "build"
Dynamic: license-file
